{"parse":{"title":"Colors","pageid":157,"wikitext":{"*":"'''Colors''' are dyes that can be used to customize the body of a [[birb]]. Users can purchase colors using rainbow stones in [[The Color Studio]].\n\nThere are currently 235 dyes available, divided between: Headpatch (38), Cheeks (32), Beak (24), Body (36), Wings (39), Belly (32), Feet (34).\n==Parts of the Body==\n:''See also: [[Stages of Growth]]''\n\n===Headpatch ===\n[[File:HeadpatchDyeBottle.jpeg|thumb|A bottle of headpatch color dye as seen in The Color Studio. The dye color is Deep Red. Color dyes for the headpatch cost 500 rainbow stones.|left]]\nThe headpatch is the top of the birb\u2019s head. When the birb is a baby, it is the same color as the birb\u2019s body. When the birb is a toddler, the headpatch is gray. When the birb becomes a child, the user can choose a random color for the birb\u2019s headpatch and wings. At this point, they can also purchase headpatch color dyes and wings color dyes in The Color Studio.{{Clear}}\n\n===Cheeks===\n[[File:CheeksDyeBottle.jpeg|thumb|A bottle of cheeks color dye as seen in The Color Studio. The dye color is Dark Brown. Color dyes for the cheeks cost 300 rainbow stones.|left]]\nThe cheeks are patches on the birb\u2019s face. When the birb is a baby, child, and toddler, they are the same color as the birb\u2019s face. When the birb becomes a teenager, the user can choose a random color for the birb\u2019s cheeks and feet. At this point, they can also purchase cheeks color dyes and feet color dyes in The Color Studio.{{Clear}}\n\n===Beak===\n[[File:BeakyDyeBottle.jpeg|thumb|A bottle of beak color dye as seen in The Color Studio. The dye color is Dark Blue. Color dyes for the beak cost 300 rainbow stones.|left]]\nThe beak is the birb\u2019s mouth. When the birb is a baby, the beak is yellow. When the birb becomes a toddler, the user can choose one of three random colors for the birb\u2019s beak. At this point, they can also purchase beak color dyes and body color dyes in The Color Studio.{{Clear}}\n===Body===\n[[File:BodyDyeBottle.jpeg|thumb|A bottle of body color dye as seen in The Color Studio. The dye color is Lavender. Color dyes for the body cost 900 rainbow stones.|left]]The body is the part of the birb that is not the head patch, cheeks, wings, or tummy. When a new user is choosing an egg, they can choose between Blue, Orange, Pink, Green, Purple, or Gray. This determines the color of the birb as a baby. When the birb becomes a toddler, the user can purchase body color dyes in The Color Studio. {{Clear}}\n\n===Wings===\n[[File:WingsDyeBottle.jpeg|thumb|A bottle of wings color dye as seen in The Color Studio. The dye color is Lilac. Color dyes for the wings cost 500 rainbow stones.|left]]The wings are the hands of the birb. When the birb is a baby. they are the same color as the birb\u2019s body. When the birb is a toddler, the wings are gray. When the birb becomes a child, the user can choose a random color for the birb\u2019s wings and headpatch. At this point, they can also purchase wing color dyes and headpatch color dyes in The Color Studio. {{Clear}}\n\n===Tummy===\n[[File:TummyDyeBottle.jpeg|thumb|A bottle of tummy color dye as seen in The Color Studio. The dye color is Tan. Color dyes for the tummy cost 500 rainbow stones.|left]]The tummy is a patch on the birb\u2019s stomach. When the birb is a baby, toddler, child, and teenager, it is the same color as the birb\u2019s body. When the birb becomes an adult, the user can choose a random color for the birb\u2019s tummy. At this point, they can also purchase tummy color dyes in The Color Studio. {{{Clear}} \n=== Feet===\n[[File:FeetDyeBottle.jpeg|thumb|A bottle of feet color dye as seen in The Color Studio. The dye color is Light Orange. Color dyes for the feet cost 300 rainbow stones.|left]]The feet are what the birb uses to journey. When the birb is a baby, toddler, and child, they are gray. When the birb becomes a teenager, the user can choose a random color for the birb\u2019s feet and cheeks. At this point, they can also purchase feet color dyes and cheeks color dyes in The Color Studio. {{Clear}} \n==Colors ==\n\n=== Headpatch ===\n<gallery>\nFile:Headpatch1.jpg|Gray, Blue, Red, <br />Orange, Yellow, Pink\nFile:Headpatch2.jpg|Black, White, Purple, <br />Teal, Light Pink, Brown\nFile:Headpatch3.jpg|Green, Royal Blue, Tan, <br />Light Purple, Burgundy, Aqua\nFile:Headpatch4.jpg|Sky Blue, Periwinkle, Mint, <br />Lavender, Light Yellow, Peach\nFile:Headpatch5.jpg|Baby Pink, Neon Green, Neon Purple, <br />Neon Yellow, Neon Pink, Dark Orange\nFile:Headpatch6.jpg|Forest Green, Slate Blue, Rose Pink, <br />Deep Red, Olive, Lilac \nFile:Headpatch7.jpg|Yellow Green, Dark Brown\n</gallery>\n\n===Cheeks===\n(Note: Cheek colors have some translucence, so they do not look exactly like the colors offered.)\n<gallery>\nFile:Cheeks1.jpg|Orange, Gray, Green, <br />Blue, Purple, Light Purple\nFile:Cheeks2.jpg|Olive, Dark Pink, Black, <br />Light Pink, Tan, Yellow\nFile:Cheeks3.jpg|White, Light Blue, Lime Green, <br />Brown, Lilac, Light Gray\nFile:Cheeks4.jpg|Burgundy, Mint, Baby Pink, <br />Light Orange, Neon Green, Neon Purple\nFile:Cheeks5.jpg|Neon Yellow, Neon Blue, Neon Pink, <br />Dark Orange, Forest Green, Slate Blue\nFile:Cheeks6.jpg|Rose Pink, Red, Yellow Green, <br /> Dark Brown\n</gallery>\n\n===Beak===\n<gallery>\nFile:Beak1.jpg|Yellow, White, Gray, <br />Orange, Black, Pink\nFile:Beak2.jpg|Red, Tan, Brown, <br />Purple, Blue, Teal\nFile:Beak3.jpg|Green, Dark Blue, Dark Green, <br /> Dark Purple, Dark Pink, Dark Orange\nFile:Beak4.jpg|Dark Yellow, Dark Gray, Dark Teal, <br /> Peach\n</gallery>\n\n===Body ===\n<gallery>\nFile:Body1.jpg|Gray, Tan, Blue, <br />Purple, Pink, Green\nFile:Body2.jpg|Beige, Light Gray, Peach, <br />Teal, Red, Yellow\nFile:Body3.jpg|Aqua, Orange, Brown, <br />Baby Pink, Baby Blue, Black\nFile:Body4.jpg|Ivory, Light Orange, Lavender, <br />Neon Green, Neon Purple, Neon Yellow\nFile:Body5.jpg|Neon Blue, Neon Pink, Dark Orange, <br />Sage Green, Slate Blue, Rose Pink\nFile:Body6.jpg|Light Red, Olive, White, <br /> Lilac, Yellow Green, Dark Brown\n</gallery>\n\n===Wings===\n<gallery>\nFile:Wings1.jpg|Light Gray, Gray, Blue, <br />Red, Orange, Yellow\nFile:Wings2.jpg|Pink, Black, White, <br />Purple, Teal, Light Pink\nFile:Wings3.jpg|Brown, Green, Royal Blue, <br />Tan, Light Purple, Burgundy\nFile:Wings4.jpg|Aqua, Sky Blue, Periwinkle, <br />Mint, Lavender, Light Yellow\nFile:Wings5.jpg|Peach, Baby Pink, Neon Green, <br />Neon Purple, Neon Yellow, Neon Pink\nFile:Wings6.jpg|Dark Orange, Forest Green, Slate Blue, <br />Rose Pink, Deep Red, Olive \nFile:Wings7.jpg|Lilac, Yellow Green, Dark Brown\n</gallery>\n\n===Tummy===\n<gallery>\nFile:Tummy1.jpg|Tan, Blue, Yellow, <br />Gray, Pink, Green\nFile:Tummy2.jpg|Orange, White, Lilac, <br />Cornflower, Red, Slate Blue\nFile:Tummy3.jpg|Lime Green, Purple, Brown, <br />Mauve, Yellow Green, Dark Gray\nFile:Tummy4.jpg|Periwinkle, Mint, Light Orange, <br />Neon Green, Neon Purple, Neon Yellow\nFile:Tummy5.jpg|Neon Blue, Neon Pink, Dark Orange, <br />Olive, Rose Pink, Light Red \nFile:Tummy6.jpg|Black, Dark Brown\n</gallery>\n\n===Feet ===\n<gallery>\nFile:Feet1.jpg|Orange, Gray, Green, <br />Blue, Purple, Light Purple\nFile:Feet2.jpg|Olive, Dark Pink, Black, <br />Light Pink, Tan, Yellow\nFile:Feet3.jpg|White, Light Blue, Lime Green, <br />Brown, Lilac, Light Gray\nFile:Feet4.jpg|Burgundy, Mint, Baby Pink, <br />Light Orange, Neon Green, Neon Purple\nFile:Feet5.jpg|Neon Yellow, Neon Blue, Neon Pink, <br />Dark Orange, Forest Green, Slate Blue\nFile:Feet6.jpg|Rose Pink, Red, Yellow Green, <br /> Dark Brown\n</gallery>\n[[Category:Colors]]"}}}